py_walk/__init__.py
py_walk/exceptions.py
py_walk/logs.py
py_walk/paths.py
py_walk/version.py
py_walk/entrypoints/__init__.py
py_walk/entrypoints/get_parser_from_file.py
py_walk/entrypoints/get_parser_from_list.py
py_walk/entrypoints/get_parser_from_text.py
py_walk/entrypoints/pattern_text_to_pattern_list.py
py_walk/entrypoints/walk.py
py_walk/lib/wildmatch/__init__.py
py_walk/lib/wildmatch/character_class_to_regex.py
py_walk/lib/wildmatch/glob_to_regex.py
py_walk/lib/wildmatch/wildmatch_match.py
py_walk/lib/wildmatch/wildmatch_to_parts.py
py_walk/models/__init__.py
py_walk/models/parser.py
py_walk/models/pattern.py
py_walk-0.3.2.dist-info/METADATA
py_walk-0.3.2.dist-info/WHEEL
py_walk-0.3.2.dist-info/licenses/LICENSE
py_walk-0.3.2.dist-info/RECORD
