Metadata-Version: 2.3
Name: py-walk
Version: 0.3.2
Summary: Filter filesystem paths based on gitignore-like patterns
Project-URL: Homepage, https://github.com/pacha/py-walk
Project-URL: Bug Tracker, https://github.com/pacha/py-walk/issues
Author-email: Andrés Sopeña Pérez <code@ehmm.org>
License-File: LICENSE
Classifier: License :: OSI Approved :: MIT License
Classifier: Operating System :: OS Independent
Classifier: Programming Language :: Python :: 3 :: Only
Classifier: Programming Language :: Python :: 3.7
Classifier: Programming Language :: Python :: 3.8
Classifier: Programming Language :: Python :: 3.9
Classifier: Programming Language :: Python :: 3.10
Classifier: Programming Language :: Python :: 3.11
Requires-Python: >=3.7
Requires-Dist: sly
Provides-Extra: code-formatting
Requires-Dist: black; extra == 'code-formatting'
Provides-Extra: dev
Requires-Dist: black; extra == 'dev'
Requires-Dist: mypy; extra == 'dev'
Requires-Dist: pytest; extra == 'dev'
Requires-Dist: pyyaml; extra == 'dev'
Requires-Dist: types-pyyaml; extra == 'dev'
Provides-Extra: publish
Requires-Dist: build; extra == 'publish'
Provides-Extra: tests
Requires-Dist: pytest; extra == 'tests'
Requires-Dist: pyyaml; extra == 'tests'
Provides-Extra: type-checks
Requires-Dist: mypy; extra == 'type-checks'
Requires-Dist: types-pyyaml; extra == 'type-checks'
